vodi.py
vodi/EnvCommand.py
vodi/Environment.py
vodi/Environments.py
vodi/LoginCommand.py
vodi/ProjectCommand.py
vodi/Projects.py
vodi/Release.py
vodi/ReleaseCommand.py
vodi/__init__.py
vodi-0.0.6.dist-info/LICENSE
vodi-0.0.6.dist-info/METADATA
vodi-0.0.6.dist-info/WHEEL
vodi-0.0.6.dist-info/entry_points.txt
vodi-0.0.6.dist-info/top_level.txt
vodi-0.0.6.dist-info/RECORD
