Metadata-Version: 2.1
Name: vodi
Version: 0.0.6
Summary: a vodafone digital automation tool
Home-page: https://github.com/pypa/sampleproject
Author: Andrea Caligiuri
Author-email: andrea.caligiuri@vodafone.com
License: UNKNOWN
Platform: UNKNOWN
Classifier: Programming Language :: Python :: 3
Classifier: License :: OSI Approved :: MIT License
Classifier: Operating System :: OS Independent
Requires-Python: >=3.7
Requires-Dist: click
Requires-Dist: atlassian-python-api
